granitewxc/__init__.py
granitewxc/datasets/__init__.py
granitewxc/datasets/merra2.py
granitewxc/decoders/__init__.py
granitewxc/decoders/downscaling.py
granitewxc/models/__init__.py
granitewxc/models/finetune_model.py
granitewxc/utils/__init__.py
granitewxc/utils/cache.py
granitewxc/utils/config.py
granitewxc/utils/data.py
granitewxc/utils/distributed.py
granitewxc/utils/downscaling_model.py
granitewxc/utils/plot.py
granitewxc-0.1.0.dist-info/WHEEL
granitewxc-0.1.0.dist-info/METADATA
granitewxc-0.1.0.dist-info/RECORD
