Metadata-Version: 2.3
Name: granitewxc
Version: 0.1.0
Summary: granite-wxc - Weather and climate downscaling model.
Author: Shraddha Singh, email = shraddha.singh@ibm.com, Julian Kuehnert, Will Torjak, Johannes Schmude, Daniel Salles Civitarese, Johannes Jakubik
Requires-Python: >=3.10
Requires-Dist: prithviwxc >= 0.1.0
Requires-Dist: xarray >= 2024.9.0
Requires-Dist: scipy
Requires-Dist: wget >= 1.21.4
Requires-Dist: pyyaml >= 6.0.2
Requires-Dist: h5netcdf >= 1.3.0
Requires-Dist: notebook ~= 7.2 ; extra == "examples"
Requires-Dist: matplotlib >= 3.8 ; extra == "examples"
Provides-Extra: examples
